Metadata-Version: 2.1
Name: covertree
Version: 1.0.0
Summary: Cover tree implementation for computing nearest neighbors in general metric spaces.
Home-page: https://github.com/Jfeatherstone/CoverTree
Author: Jack Featherstone
Author-email: jack.featherstone@oist.jp
License: New BSD License
Platform: UNKNOWN
Classifier: Programming Language :: Python :: 3.7
Classifier: Operating System :: OS Independent
License-File: LICENSE.txt
